ConsoleDialogs/__init__.py
ConsoleDialogs/cursesdialogs.py
ConsoleDialogs/cursesutils.py
ConsoleDialogs/keywords.py
ConsoleDialogs/rawdialogs.py
robotframework_consoledialogs-1.1.3.dist-info/LICENSE.txt
robotframework_consoledialogs-1.1.3.dist-info/METADATA
robotframework_consoledialogs-1.1.3.dist-info/WHEEL
robotframework_consoledialogs-1.1.3.dist-info/top_level.txt
robotframework_consoledialogs-1.1.3.dist-info/RECORD
