Metadata-Version: 2.1
Name: robotframework-consoledialogs
Version: 1.1.3
Summary: A pure console replacement for the Robot Framework Dialogs library.
Home-page: http://github.com/tw39124-1/robotframework-consoledialogs
Author: tw39124-1
License: MIT
Download-URL: https://github.com/tw39124-1/robotframework-consoledialogs/archive/v1.1.3.tar.gz
Keywords: robotframework dialogs console ui
Platform: UNKNOWN
Classifier: Framework :: Robot Framework
Classifier: License :: OSI Approved :: MIT License
Classifier: Programming Language :: Python
Classifier: Programming Language :: Python :: 3.4
Classifier: Programming Language :: Python :: 3.5
Classifier: Programming Language :: Python :: 3.6
Classifier: Programming Language :: Python :: 3.7
Classifier: Environment :: Console :: Curses
Classifier: Operating System :: OS Independent
Requires-Dist: setuptools
Requires-Dist: wheel
Requires-Dist: robotframework
Provides-Extra: dev
